{
  "questions": [
    {
      "question": "Q64:- The term 'Offside' is associated with which sport?",
      "options": [
        "Cricket",
        "Football",
        "Hockey",
        "Basketball"
      ],
      "answer": "Football",
      "category": "GK",
      "source": "SSC GD 2025",
      "date": "2025-11-25",
      "shift": "Afternoon"
    },
    {
      "question": "Q45:-Which of the following is a non-renewable source of energy?",
      "options": [
        "Solar energy",
        "Wind energy",
        "Coal",
        "Hydroelectric energy"
      ],
      "answer": "Coal",
      "category": "GK",
      "source": "SSC MTS 2022",
      "date": "2022-07-25",
      "shift": "Afternoon"
    },
    {
      "question": "Q26:-The famous Sanchi Stupa is located in which Indian state?",
      "options": [
        "Uttar Pradesh",
        "Bihar",
        "Madhya Pradesh",
        "Maharashtra"
      ],
      "answer": "Madhya Pradesh",
      "category": "GK",
      "source": "SSC CGL 2023",
      "date": "2023-04-10",
      "shift": "Morning"
    },
    {
      "question": "Q4:-Who invented the telephone?",
      "options": [
        "Alexander Graham Bell",
        "Thomas Edison",
        "Guglielmo Marconi",
        "Nikola Tesla"
      ],
      "answer": "Alexander Graham Bell",
      "category": "GK",
      "source": "SSC CHSL 2020",
      "date": "2020-09-10",
      "shift": "Evening"
    },
    {
      "question": "Q29:-Who is known as the 'Father of Indian Cinema'?",
      "options": [
        "Satyajit Ray",
        "Dadasaheb Phalke",
        "Raj Kapoor",
        "Guru Dutt"
      ],
      "answer": "Dadasaheb Phalke",
      "category": "GK",
      "source": "SSC MTS 2023",
      "date": "2023-09-22",
      "shift": "Morning"
    },
    {
      "question": "Q99:-The 'Tropic of Cancer' passes through how many Indian states?",
      "options": [
        "6",
        "7",
        "8",
        "9"
      ],
      "answer": "8",
      "category": "GK",
      "source": "SSC MTS 2022",
      "date": "2022-07-01",
      "shift": "Evening"
    },
    {
      "question": "Q98:-The highest dam in India is:",
      "options": [
        "Bhakra Dam",
        "Tehri Dam",
        "Hirakud Dam",
        "Nagarjuna Sagar Dam"
      ],
      "answer": "Tehri Dam",
      "category": "GK",
      "source": "SSC CGL 2023",
      "date": "2023-05-05",
      "shift": "Afternoon"
    },
    {
      "question": "Q10:-Who was known as the 'Iron Man of India'?",
      "options": [
        "Jawaharlal Nehru",
        "Vallabhbhai Patel",
        "Subhas Chandra Bose",
        "Mahatma Gandhi"
      ],
      "answer": "Vallabhbhai Patel",
      "category": "GK",
      "source": "SSC CHSL 2021",
      "date": "2021-04-22",
      "shift": "Evening"
    },
    {
      "question": "Q74:-The 'Gol Gumbaz' is located in which state?",
      "options": [
        "Karnataka",
        "Maharashtra",
        "Telangana",
        "Andhra Pradesh"
      ],
      "answer": "Karnataka",
      "category": "GK",
      "source": "SSC MTS 2022",
      "date": "2022-08-10",
      "shift": "Afternoon"
    },
    {
      "question": "Q30:- The headquarters of the 'International Cricket Council' (ICC) is located in:",
      "options": [
        "London",
        "Dubai",
        "Sydney",
        "Mumbai"
      ],
      "answer": "Dubai",
      "category": "GK",
      "source": "SSC CHSL 2024",
      "date": "2024-04-12",
      "shift": "Evening"
    }
  ]
}