{
  "questions": [
    {
      "question": "Q52:- The 'Golden Temple' is located in which Indian city?",
      "options": [
        "Delhi",
        "Varanasi",
        "Amritsar",
        "Ludhiana"
      ],
      "answer": "Amritsar",
      "category": "GK",
      "source": "SSC GD 2025",
      "date": "2025-08-28",
      "shift": "Morning"
    },
    {
      "question": "Q61:- The largest river in India by volume is:",
      "options": [
        "Ganga",
        "Brahmaputra",
        "Godavari",
        "Indus"
      ],
      "answer": "Brahmaputra",
      "category": "GK",
      "source": "SSC CGL 2025",
      "date": "2025-11-05",
      "shift": "Morning"
    },
    {
      "question": "Q21:-The Preamble to the Indian Constitution is based on the 'Objective Resolution' drafted by:",
      "options": [
        "Dr. B.R. Ambedkar",
        "Jawaharlal Nehru",
        "Sardar Vallabhbhai Patel",
        "Rajendra Prasad"
      ],
      "answer": "Jawaharlal Nehru",
      "category": "GK",
      "source": "SSC CHSL 2023",
      "date": "2023-03-01",
      "shift": "Evening"
    },
    {
      "question": "Q41:- The 'Zero Hour' in the Indian Parliament refers to:",
      "options": [
        "The first hour of the session",
        "The time immediately following the Question Hour",
        "The last hour of the session",
        "The time when no business is transacted"
      ],
      "answer": "The time immediately following the Question Hour",
      "category": "GK",
      "source": "SSC CGL 2025",
      "date": "2025-06-01",
      "shift": "Morning"
    },
    {
      "question": "Q59:- The 'Grand Canyon' is located in which country?",
      "options": [
        "Canada",
        "USA",
        "Mexico",
        "Australia"
      ],
      "answer": "USA",
      "category": "GK",
      "source": "SSC MTS 2025",
      "date": "2025-10-10",
      "shift": "Afternoon"
    },
    {
      "question": "Q47:- The smallest Union Territory in India by population is:",
      "options": [
        "Chandigarh",
        "Lakshadweep",
        "Daman and Diu",
        "Puducherry"
      ],
      "answer": "Lakshadweep",
      "category": "GK",
      "source": "SSC MTS 2025",
      "date": "2025-07-10",
      "shift": "Morning"
    },
    {
      "question": "Q24:- The 'World Health Organization' (WHO) headquarters is located in:",
      "options": [
        "New York",
        "Geneva",
        "Paris",
        "London"
      ],
      "answer": "Geneva",
      "category": "GK",
      "source": "SSC GD 2024",
      "date": "2024-06-20",
      "shift": "Afternoon"
    },
    {
      "question": "Q82:-The 'National Science Day' in India is celebrated on:",
      "options": [
        "January 15",
        "February 28",
        "March 22",
        "April 7"
      ],
      "answer": "February 28",
      "category": "GK",
      "source": "SSC GD 2022",
      "date": "2022-12-18",
      "shift": "Morning"
    },
    {
      "question": "Q1:- Who was the founder of the Mughal Empire in India?",
      "options": [
        "Akbar",
        "Humayun",
        "Babur",
        "Shah Jahan"
      ],
      "answer": "Babur",
      "category": "GK",
      "source": "SSC CGL 2024",
      "date": "2024-07-01",
      "shift": "Morning"
    },
    {
      "question": "Q81:- The 'Tsunami' is caused by:",
      "options": [
        "Strong winds",
        "Undersea earthquakes",
        "Volcanic eruptions",
        "Heavy rainfall"
      ],
      "answer": "Undersea earthquakes",
      "category": "GK",
      "source": "SSC CGL 2025",
      "date": "2025-06-10",
      "shift": "Evening"
    }
  ]
}