{
  "questions": [
    {
      "question": "Q84:- The 'UNESCO' headquarters is located in:",
      "options": [
        "Rome",
        "Paris",
        "London",
        "Geneva"
      ],
      "answer": "Paris",
      "category": "GK",
      "source": "SSC GD 2025",
      "date": "2025-05-08",
      "shift": "Afternoon"
    },
    {
      "question": "Q12:-The 'Chipko Movement' is associated with the conservation of which of the following?",
      "options": [
        "Forests",
        "Wetlands",
        "Rivers",
        "Mountains"
      ],
      "answer": "Forests",
      "category": "GK",
      "source": "SSC CHSL 2023",
      "date": "2023-08-05",
      "shift": "Afternoon"
    },
    {
      "question": "Q13:- The instrument used to measure electric current is:",
      "options": [
        "Voltmeter",
        "Ammeter",
        "Ohmmeter",
        "Galvanometer"
      ],
      "answer": "Ammeter",
      "category": "GK",
      "source": "SSC CGL 2024",
      "date": "2024-10-10",
      "shift": "Morning"
    },
    {
      "question": "Q75:-The largest ocean in the world is:",
      "options": [
        "Atlantic Ocean",
        "Indian Ocean",
        "Pacific Ocean",
        "Arctic Ocean"
      ],
      "answer": "Pacific Ocean",
      "category": "GK",
      "source": "SSC GD 2023",
      "date": "2023-02-15",
      "shift": "Morning"
    },
    {
      "question": "Q90:-The minimum age to become a member of Rajya Sabha is:",
      "options": [
        "25 years",
        "30 years",
        "35 years",
        "40 years"
      ],
      "answer": "30 years",
      "category": "GK",
      "source": "SSC MTS 2023",
      "date": "2023-07-20",
      "shift": "Morning"
    },
    {
      "question": "Q8:-What is the capital of Arunachal Pradesh?",
      "options": [
        "Itanagar",
        "Dispur",
        "Guwahati",
        "Shillong"
      ],
      "answer": "Itanagar",
      "category": "GK",
      "source": "SSC CHSL 2020",
      "date": "2020-08-11",
      "shift": "Evening"
    },
    {
      "question": "Q73:-The 'Durand Line' is the border between which two countries?",
      "options": [
        "India and Pakistan",
        "India and China",
        "Pakistan and Afghanistan",
        "India and Bangladesh"
      ],
      "answer": "Pakistan and Afghanistan",
      "category": "GK",
      "source": "SSC CGL 2021",
      "date": "2021-06-25",
      "shift": "Morning"
    },
    {
      "question": "Q21:-The Preamble to the Indian Constitution is based on the 'Objective Resolution' drafted by:",
      "options": [
        "Dr. B.R. Ambedkar",
        "Jawaharlal Nehru",
        "Sardar Vallabhbhai Patel",
        "Rajendra Prasad"
      ],
      "answer": "Jawaharlal Nehru",
      "category": "GK",
      "source": "SSC CHSL 2023",
      "date": "2023-03-01",
      "shift": "Evening"
    },
    {
      "question": "Q89:-The 'International Yoga Day' is celebrated on:",
      "options": [
        "June 5",
        "June 21",
        "July 11",
        "August 12"
      ],
      "answer": "June 21",
      "category": "GK",
      "source": "SSC GD 2023",
      "date": "2023-01-30",
      "shift": "Afternoon"
    },
    {
      "question": "Q54:- The 'World Heritage Day' is celebrated on:",
      "options": [
        "April 18",
        "June 5",
        "July 11",
        "October 24"
      ],
      "answer": "April 18",
      "category": "GK",
      "source": "SSC CHSL 2024",
      "date": "2024-10-15",
      "shift": "Afternoon"
    }
  ]
}