{
  "questions": [
    {
      "question": "Q85:-The world's largest flower is:",
      "options": [
        "Rose",
        "Sunflower",
        "Rafflesia Arnoldii",
        "Lotus"
      ],
      "answer": "Rafflesia Arnoldii",
      "category": "GK",
      "source": "SSC MTS 2023",
      "date": "2023-07-15",
      "shift": "Afternoon"
    },
    {
      "question": "Q95:-The famous 'Charminar' is located in which Indian city?",
      "options": [
        "Delhi",
        "Lucknow",
        "Hyderabad",
        "Agra"
      ],
      "answer": "Hyderabad",
      "category": "GK",
      "source": "SSC GD 2023",
      "date": "2023-02-20",
      "shift": "Evening"
    },
    {
      "question": "Q60:- The 'First Five-Year Plan' in India was launched in:",
      "options": [
        "1947",
        "1950",
        "1951",
        "1956"
      ],
      "answer": "1951",
      "category": "GK",
      "source": "SSC GD 2025",
      "date": "2025-10-20",
      "shift": "Morning"
    },
    {
      "question": "Q54:-The 'Quit India Movement' was launched in which year?",
      "options": [
        "1940",
        "1942",
        "1945",
        "1947"
      ],
      "answer": "1942",
      "category": "GK",
      "source": "SSC MTS 2023",
      "date": "2023-07-03",
      "shift": "Morning"
    },
    {
      "question": "Q54:- The 'World Heritage Day' is celebrated on:",
      "options": [
        "April 18",
        "June 5",
        "July 11",
        "October 24"
      ],
      "answer": "April 18",
      "category": "GK",
      "source": "SSC CHSL 2024",
      "date": "2024-10-15",
      "shift": "Afternoon"
    },
    {
      "question": "Q60:-The deepest ocean trench in the world is:",
      "options": [
        "Java Trench",
        "Puerto Rico Trench",
        "Mariana Trench",
        "Kermadec Trench"
      ],
      "answer": "Mariana Trench",
      "category": "GK",
      "source": "SSC CHSL 2023",
      "date": "2023-08-10",
      "shift": "Morning"
    },
    {
      "question": "Q1:-Who was the first President of India?",
      "options": [
        "Rajendra Prasad",
        "S. Radhakrishnan",
        "Zakir Husain",
        "V. V. Giri"
      ],
      "answer": "Rajendra Prasad",
      "category": "GK",
      "source": "SSC CGL 2023",
      "date": "2023-07-14",
      "shift": "Morning"
    },
    {
      "question": "Q80:-The deepest lake in the world is:",
      "options": [
        "Lake Superior",
        "Lake Baikal",
        "Great Slave Lake",
        "Lake Tanganyika"
      ],
      "answer": "Lake Baikal",
      "category": "GK",
      "source": "SSC CHSL 2023",
      "date": "2023-08-22",
      "shift": "Evening"
    },
    {
      "question": "Q67:- The largest railway network in the world is in which country?",
      "options": [
        "China",
        "India",
        "USA",
        "Russia"
      ],
      "answer": "USA",
      "category": "GK",
      "source": "SSC MTS 2025",
      "date": "2025-12-10",
      "shift": "Morning"
    },
    {
      "question": "Q55:- The 'Bharat Ratna' award was instituted in which year?",
      "options": [
        "1950",
        "1952",
        "1954",
        "1956"
      ],
      "answer": "1954",
      "category": "GK",
      "source": "SSC MTS 2025",
      "date": "2025-09-05",
      "shift": "Morning"
    }
  ]
}