{
  "questions": [
    {
      "question": "Q22:-Which of the following is a classical dance form from Kerala?",
      "options": [
        "Bharatnatyam",
        "Kathakali",
        "Kuchipudi",
        "Odissi"
      ],
      "answer": "Kathakali",
      "category": "GK",
      "source": "SSC MTS 2022",
      "date": "2022-09-15",
      "shift": "Morning"
    },
    {
      "question": "Q77:- The largest plateau in the world is:",
      "options": [
        "Deccan Plateau",
        "Tibetan Plateau",
        "Patagonian Plateau",
        "Colorado Plateau"
      ],
      "answer": "Tibetan Plateau",
      "category": "GK",
      "source": "SSC CGL 2025",
      "date": "2025-05-01",
      "shift": "Morning"
    },
    {
      "question": "Q57:- The 'United Nations Organization' (UNO) was established in which year?",
      "options": [
        "1942",
        "1945",
        "1948",
        "1950"
      ],
      "answer": "1945",
      "category": "GK",
      "source": "SSC CGL 2025",
      "date": "2025-10-01",
      "shift": "Morning"
    },
    {
      "question": "Q14:- Who founded the 'Ramakrishna Mission'?",
      "options": [
        "Swami Dayanand Saraswati",
        "Ramakrishna Paramahamsa",
        "Swami Vivekananda",
        "Raja Ram Mohan Roy"
      ],
      "answer": "Swami Vivekananda",
      "category": "GK",
      "source": "SSC CHSL 2023",
      "date": "2023-09-15",
      "shift": "Afternoon"
    },
    {
      "question": "Q67:-The study of celestial bodies and the universe is called:",
      "options": [
        "Geology",
        "Biology",
        "Astronomy",
        "Physics"
      ],
      "answer": "Astronomy",
      "category": "GK",
      "source": "SSC CHSL 2021",
      "date": "2021-07-08",
      "shift": "Afternoon"
    },
    {
      "question": "Q92:- The 'Battle of Khanwa' was fought between Babur and which Rajput ruler?",
      "options": [
        "Prithviraj Chauhan",
        "Rana Sanga",
        "Maharana Pratap",
        "Raja Man Singh"
      ],
      "answer": "Rana Sanga",
      "category": "GK",
      "source": "SSC GD 2025",
      "date": "2025-07-12",
      "shift": "Evening"
    },
    {
      "question": "Q68:-The process by which plants make their own food is called:",
      "options": [
        "Respiration",
        "Photosynthesis",
        "Transpiration",
        "Fermentation"
      ],
      "answer": "Photosynthesis",
      "category": "GK",
      "source": "SSC CGL 2022",
      "date": "2022-09-28",
      "shift": "Morning"
    },
    {
      "question": "Q27:- The 'Bharat Natyam' dance form originated from which state?",
      "options": [
        "Kerala",
        "Karnataka",
        "Tamil Nadu",
        "Andhra Pradesh"
      ],
      "answer": "Tamil Nadu",
      "category": "GK",
      "source": "SSC MTS 2025",
      "date": "2025-01-20",
      "shift": "Evening"
    },
    {
      "question": "Q15:-What is the chemical symbol for gold?",
      "options": [
        "Ag",
        "Au",
        "Cu",
        "Fe"
      ],
      "answer": "Au",
      "category": "GK",
      "source": "SSC GD 2023",
      "date": "2023-01-18",
      "shift": "Evening"
    },
    {
      "question": "Q84:- The 'UNESCO' headquarters is located in:",
      "options": [
        "Rome",
        "Paris",
        "London",
        "Geneva"
      ],
      "answer": "Paris",
      "category": "GK",
      "source": "SSC GD 2025",
      "date": "2025-05-08",
      "shift": "Afternoon"
    }
  ]
}