{
  "questions": [
    {
      "question": "Q73:- The 'Quit India Movement' slogan 'Do or Die' was given by:",
      "options": [
        "Subhas Chandra Bose",
        "Mahatma Gandhi",
        "Jawaharlal Nehru",
        "Sardar Vallabhbhai Patel"
      ],
      "answer": "Mahatma Gandhi",
      "category": "GK",
      "source": "SSC CGL 2025",
      "date": "2025-04-20",
      "shift": "Evening"
    },
    {
      "question": "Q95:-The famous 'Charminar' is located in which Indian city?",
      "options": [
        "Delhi",
        "Lucknow",
        "Hyderabad",
        "Agra"
      ],
      "answer": "Hyderabad",
      "category": "GK",
      "source": "SSC GD 2023",
      "date": "2023-02-20",
      "shift": "Evening"
    },
    {
      "question": "Q97:- The 'Currency of South Korea' is:",
      "options": [
        "Yuan",
        "Yen",
        "Won",
        "Baht"
      ],
      "answer": "Won",
      "category": "GK",
      "source": "SSC CGL 2025",
      "date": "2025-09-01",
      "shift": "Afternoon"
    },
    {
      "question": "Q81:-Who was the first Indian to go to space?",
      "options": [
        "Kalpana Chawla",
        "Rakesh Sharma",
        "Sunita Williams",
        "Ravish Malhotra"
      ],
      "answer": "Rakesh Sharma",
      "category": "GK",
      "source": "SSC CGL 2021",
      "date": "2021-11-01",
      "shift": "Morning"
    },
    {
      "question": "Q68:- The 'World Water Day' is celebrated on:",
      "options": [
        "March 22",
        "April 22",
        "June 5",
        "July 11"
      ],
      "answer": "March 22",
      "category": "GK",
      "source": "SSC GD 2025",
      "date": "2025-12-18",
      "shift": "Evening"
    },
    {
      "question": "Q79:-The sport of 'Kabaddi' originated in which country?",
      "options": [
        "China",
        "India",
        "Bangladesh",
        "Nepal"
      ],
      "answer": "India",
      "category": "GK",
      "source": "SSC MTS 2023",
      "date": "2023-06-20",
      "shift": "Morning"
    },
    {
      "question": "Q17:- The largest state in India by area is:",
      "options": [
        "Madhya Pradesh",
        "Maharashtra",
        "Rajasthan",
        "Uttar Pradesh"
      ],
      "answer": "Rajasthan",
      "category": "GK",
      "source": "SSC CGL 2024",
      "date": "2024-11-01",
      "shift": "Morning"
    },
    {
      "question": "Q50:-The first battle of Panipat was fought in which year?",
      "options": [
        "1526",
        "1556",
        "1761",
        "1757"
      ],
      "answer": "1526",
      "category": "GK",
      "source": "SSC MTS 2023",
      "date": "2023-06-15",
      "shift": "Morning"
    },
    {
      "question": "Q71:-The gas used in balloons and airships is:",
      "options": [
        "Oxygen",
        "Nitrogen",
        "Helium",
        "Argon"
      ],
      "answer": "Helium",
      "category": "GK",
      "source": "SSC CGL 2023",
      "date": "2023-07-01",
      "shift": "Morning"
    },
    {
      "question": "Q31:- The smallest bone in the human body is:",
      "options": [
        "Femur",
        "Stapes",
        "Patella",
        "Humerus"
      ],
      "answer": "Stapes",
      "category": "GK",
      "source": "SSC MTS 2025",
      "date": "2025-03-01",
      "shift": "Morning"
    }
  ]
}