{
  "questions": [
    {
      "question": "Q93:- The 'Indian Standard Time' (IST) is based on the longitude of:",
      "options": [
        "82.5\u00b0 E",
        "78.5\u00b0 E",
        "90.5\u00b0 E",
        "75.5\u00b0 E"
      ],
      "answer": "82.5\u00b0 E",
      "category": "GK",
      "source": "SSC CGL 2025",
      "date": "2025-08-10",
      "shift": "Morning"
    },
    {
      "question": "Q87:- The 'Kochi International Airport' is the first airport in the world to be fully powered by:",
      "options": [
        "Wind energy",
        "Solar energy",
        "Hydroelectric energy",
        "Geothermal energy"
      ],
      "answer": "Solar energy",
      "category": "GK",
      "source": "SSC MTS 2025",
      "date": "2025-06-20",
      "shift": "Evening"
    },
    {
      "question": "Q60:-The deepest ocean trench in the world is:",
      "options": [
        "Java Trench",
        "Puerto Rico Trench",
        "Mariana Trench",
        "Kermadec Trench"
      ],
      "answer": "Mariana Trench",
      "category": "GK",
      "source": "SSC CHSL 2023",
      "date": "2023-08-10",
      "shift": "Morning"
    },
    {
      "question": "Q47:-Who built the 'Red Fort' in Delhi?",
      "options": [
        "Akbar",
        "Humayun",
        "Shah Jahan",
        "Aurangzeb"
      ],
      "answer": "Shah Jahan",
      "category": "GK",
      "source": "SSC CHSL 2021",
      "date": "2021-05-20",
      "shift": "Morning"
    },
    {
      "question": "Q26:-The famous Sanchi Stupa is located in which Indian state?",
      "options": [
        "Uttar Pradesh",
        "Bihar",
        "Madhya Pradesh",
        "Maharashtra"
      ],
      "answer": "Madhya Pradesh",
      "category": "GK",
      "source": "SSC CGL 2023",
      "date": "2023-04-10",
      "shift": "Morning"
    },
    {
      "question": "Q39:- The largest island in the world is:",
      "options": [
        "Australia",
        "Greenland",
        "New Guinea",
        "Madagascar"
      ],
      "answer": "Greenland",
      "category": "GK",
      "source": "SSC MTS 2025",
      "date": "2025-05-30",
      "shift": "Morning"
    },
    {
      "question": "Q7:- The largest freshwater lake in the world is:",
      "options": [
        "Lake Superior",
        "Lake Baikal",
        "Great Bear Lake",
        "Lake Victoria"
      ],
      "answer": "Lake Superior",
      "category": "GK",
      "source": "SSC MTS 2024",
      "date": "2024-06-05",
      "shift": "Morning"
    },
    {
      "question": "Q1:- Who was the founder of the Mughal Empire in India?",
      "options": [
        "Akbar",
        "Humayun",
        "Babur",
        "Shah Jahan"
      ],
      "answer": "Babur",
      "category": "GK",
      "source": "SSC CGL 2024",
      "date": "2024-07-01",
      "shift": "Morning"
    },
    {
      "question": "Q87:-The second largest planet in our solar system is:",
      "options": [
        "Mars",
        "Jupiter",
        "Saturn",
        "Uranus"
      ],
      "answer": "Saturn",
      "category": "GK",
      "source": "SSC CHSL 2021",
      "date": "2021-04-10",
      "shift": "Evening"
    },
    {
      "question": "Q61:- The largest river in India by volume is:",
      "options": [
        "Ganga",
        "Brahmaputra",
        "Godavari",
        "Indus"
      ],
      "answer": "Brahmaputra",
      "category": "GK",
      "source": "SSC CGL 2025",
      "date": "2025-11-05",
      "shift": "Morning"
    }
  ]
}