{
  "questions": [
    {
      "question": "Q51:-Which of the following is a unit of energy?",
      "options": [
        "Watt",
        "Joule",
        "Ampere",
        "Volt"
      ],
      "answer": "Joule",
      "category": "GK",
      "source": "SSC CGL 2023",
      "date": "2023-03-20",
      "shift": "Morning"
    },
    {
      "question": "Q59:-Which country is known as the 'Land of the Rising Sun'?",
      "options": [
        "China",
        "South Korea",
        "Japan",
        "Thailand"
      ],
      "answer": "Japan",
      "category": "GK",
      "source": "SSC MTS 2022",
      "date": "2022-09-05",
      "shift": "Evening"
    },
    {
      "question": "Q78:- The 'Khajuraho Group of Monuments' is located in which Indian state?",
      "options": [
        "Uttar Pradesh",
        "Madhya Pradesh",
        "Rajasthan",
        "Odisha"
      ],
      "answer": "Madhya Pradesh",
      "category": "GK",
      "source": "SSC CHSL 2025",
      "date": "2025-04-10",
      "shift": "Afternoon"
    },
    {
      "question": "Q29:-Who is known as the 'Father of Indian Cinema'?",
      "options": [
        "Satyajit Ray",
        "Dadasaheb Phalke",
        "Raj Kapoor",
        "Guru Dutt"
      ],
      "answer": "Dadasaheb Phalke",
      "category": "GK",
      "source": "SSC MTS 2023",
      "date": "2023-09-22",
      "shift": "Morning"
    },
    {
      "question": "Q28:-The largest freshwater lake in India is:",
      "options": [
        "Dal Lake",
        "Wular Lake",
        "Chilika Lake",
        "Sambhar Lake"
      ],
      "answer": "Wular Lake",
      "category": "GK",
      "source": "SSC CGL 2021",
      "date": "2021-06-01",
      "shift": "Evening"
    },
    {
      "question": "Q11:- Which is the largest bone in the human body?",
      "options": [
        "Stapes",
        "Femur",
        "Tibia",
        "Fibula"
      ],
      "answer": "Femur",
      "category": "GK",
      "source": "SSC MTS 2024",
      "date": "2024-04-20",
      "shift": "Evening"
    },
    {
      "question": "Q71:-The gas used in balloons and airships is:",
      "options": [
        "Oxygen",
        "Nitrogen",
        "Helium",
        "Argon"
      ],
      "answer": "Helium",
      "category": "GK",
      "source": "SSC CGL 2023",
      "date": "2023-07-01",
      "shift": "Morning"
    },
    {
      "question": "Q93:- The 'Indian Standard Time' (IST) is based on the longitude of:",
      "options": [
        "82.5\u00b0 E",
        "78.5\u00b0 E",
        "90.5\u00b0 E",
        "75.5\u00b0 E"
      ],
      "answer": "82.5\u00b0 E",
      "category": "GK",
      "source": "SSC CGL 2025",
      "date": "2025-08-10",
      "shift": "Morning"
    },
    {
      "question": "Q5:- The currency of China is:",
      "options": [
        "Won",
        "Yen",
        "Yuan",
        "Rupee"
      ],
      "answer": "Yuan",
      "category": "GK",
      "source": "SSC CGL 2024",
      "date": "2024-08-15",
      "shift": "Morning"
    },
    {
      "question": "Q91:- The 'Right to Information Act' (RTI) came into force in India in which year?",
      "options": [
        "2002",
        "2005",
        "2007",
        "2010"
      ],
      "answer": "2005",
      "category": "GK",
      "source": "SSC MTS 2025",
      "date": "2025-07-05",
      "shift": "Morning"
    }
  ]
}