{
  "questions": [
    {
      "question": "Q67:- The largest railway network in the world is in which country?",
      "options": [
        "China",
        "India",
        "USA",
        "Russia"
      ],
      "answer": "USA",
      "category": "GK",
      "source": "SSC MTS 2025",
      "date": "2025-12-10",
      "shift": "Morning"
    },
    {
      "question": "Q93:- The 'Indian Standard Time' (IST) is based on the longitude of:",
      "options": [
        "82.5\u00b0 E",
        "78.5\u00b0 E",
        "90.5\u00b0 E",
        "75.5\u00b0 E"
      ],
      "answer": "82.5\u00b0 E",
      "category": "GK",
      "source": "SSC CGL 2025",
      "date": "2025-08-10",
      "shift": "Morning"
    },
    {
      "question": "Q64:-The 'Beti Bachao, Beti Padhao' scheme was launched to address which issue?",
      "options": [
        "Child labor",
        "Girl child education and gender ratio",
        "Malnutrition",
        "Poverty alleviation"
      ],
      "answer": "Girl child education and gender ratio",
      "category": "GK",
      "source": "SSC CHSL 2020",
      "date": "2020-08-20",
      "shift": "Morning"
    },
    {
      "question": "Q60:- The 'First Five-Year Plan' in India was launched in:",
      "options": [
        "1947",
        "1950",
        "1951",
        "1956"
      ],
      "answer": "1951",
      "category": "GK",
      "source": "SSC GD 2025",
      "date": "2025-10-20",
      "shift": "Morning"
    },
    {
      "question": "Q54:- The 'World Heritage Day' is celebrated on:",
      "options": [
        "April 18",
        "June 5",
        "July 11",
        "October 24"
      ],
      "answer": "April 18",
      "category": "GK",
      "source": "SSC CHSL 2024",
      "date": "2024-10-15",
      "shift": "Afternoon"
    },
    {
      "question": "Q27:-Which of the following is a direct tax?",
      "options": [
        "GST",
        "Sales Tax",
        "Income Tax",
        "Excise Duty"
      ],
      "answer": "Income Tax",
      "category": "GK",
      "source": "SSC CHSL 2022",
      "date": "2022-04-18",
      "shift": "Afternoon"
    },
    {
      "question": "Q26:-The famous Sanchi Stupa is located in which Indian state?",
      "options": [
        "Uttar Pradesh",
        "Bihar",
        "Madhya Pradesh",
        "Maharashtra"
      ],
      "answer": "Madhya Pradesh",
      "category": "GK",
      "source": "SSC CGL 2023",
      "date": "2023-04-10",
      "shift": "Morning"
    },
    {
      "question": "Q65:- The 'National Song of India' 'Vande Mataram' was composed by:",
      "options": [
        "Rabindranath Tagore",
        "Bankim Chandra Chatterjee",
        "Muhammad Iqbal",
        "Sarojini Naidu"
      ],
      "answer": "Bankim Chandra Chatterjee",
      "category": "GK",
      "source": "SSC CGL 2025",
      "date": "2025-12-01",
      "shift": "Morning"
    },
    {
      "question": "Q11:-Which of the following is not a UN permanent member country?",
      "options": [
        "France",
        "Canada",
        "China",
        "Russia"
      ],
      "answer": "Canada",
      "category": "GK",
      "source": "SSC CGL 2022",
      "date": "2022-09-01",
      "shift": "Morning"
    },
    {
      "question": "Q24:-The first artificial satellite launched by India was:",
      "options": [
        "Rohini",
        "Bhaskara",
        "Aryabhata",
        "Chandrayaan-1"
      ],
      "answer": "Aryabhata",
      "category": "GK",
      "source": "SSC CGL 2020",
      "date": "2020-02-28",
      "shift": "Evening"
    }
  ]
}