{
  "questions": [
    {
      "question": "Q53:-Which Indian state is known as the 'Spice Garden of India'?",
      "options": [
        "Kerala",
        "Karnataka",
        "Tamil Nadu",
        "Andhra Pradesh"
      ],
      "answer": "Kerala",
      "category": "GK",
      "source": "SSC CGL 2021",
      "date": "2021-12-01",
      "shift": "Morning"
    },
    {
      "question": "Q30:-The first Indian woman to win an Olympic medal was:",
      "options": [
        "P. T. Usha",
        "Karnam Malleswari",
        "Saina Nehwal",
        "Mary Kom"
      ],
      "answer": "Karnam Malleswari",
      "category": "GK",
      "source": "SSC GD 2022",
      "date": "2022-11-14",
      "shift": "Morning"
    },
    {
      "question": "Q54:-The 'Quit India Movement' was launched in which year?",
      "options": [
        "1940",
        "1942",
        "1945",
        "1947"
      ],
      "answer": "1942",
      "category": "GK",
      "source": "SSC MTS 2023",
      "date": "2023-07-03",
      "shift": "Morning"
    },
    {
      "question": "Q3:-The headquarters of the Asian Development Bank is located in which city?",
      "options": [
        "Tokyo",
        "Manila",
        "New Delhi",
        "Bangkok"
      ],
      "answer": "Manila",
      "category": "GK",
      "source": "SSC CGL 2021",
      "date": "2021-12-05",
      "shift": "Morning"
    },
    {
      "question": "Q4:- Who wrote the epic 'Ramayana'?",
      "options": [
        "Valmiki",
        "Tulsidas",
        "Vyasa",
        "Kalidasa"
      ],
      "answer": "Valmiki",
      "category": "GK",
      "source": "SSC GD 2024",
      "date": "2024-01-25",
      "shift": "Afternoon"
    },
    {
      "question": "Q85:- The 'International Court of Justice' is located in:",
      "options": [
        "New York",
        "London",
        "The Hague",
        "Brussels"
      ],
      "answer": "The Hague",
      "category": "GK",
      "source": "SSC CGL 2025",
      "date": "2025-07-01",
      "shift": "Morning"
    },
    {
      "question": "Q70:-The smallest union territory of India is:",
      "options": [
        "Chandigarh",
        "Lakshadweep",
        "Daman and Diu",
        "Puducherry"
      ],
      "answer": "Lakshadweep",
      "category": "GK",
      "source": "SSC MTS 2023",
      "date": "2023-05-20",
      "shift": "Evening"
    },
    {
      "question": "Q12:- The 'Battle of Plassey' was fought in which year?",
      "options": [
        "1757",
        "1764",
        "1773",
        "1857"
      ],
      "answer": "1757",
      "category": "GK",
      "source": "SSC GD 2024",
      "date": "2024-03-01",
      "shift": "Morning"
    },
    {
      "question": "Q11:- Which is the largest bone in the human body?",
      "options": [
        "Stapes",
        "Femur",
        "Tibia",
        "Fibula"
      ],
      "answer": "Femur",
      "category": "GK",
      "source": "SSC MTS 2024",
      "date": "2024-04-20",
      "shift": "Evening"
    },
    {
      "question": "Q24:-The first artificial satellite launched by India was:",
      "options": [
        "Rohini",
        "Bhaskara",
        "Aryabhata",
        "Chandrayaan-1"
      ],
      "answer": "Aryabhata",
      "category": "GK",
      "source": "SSC CGL 2020",
      "date": "2020-02-28",
      "shift": "Evening"
    }
  ]
}