{
  "questions": [
    {
      "question": "Q26:- The longest river in Asia is:",
      "options": [
        "Ganga",
        "Yellow River",
        "Yangtze River",
        "Mekong River"
      ],
      "answer": "Yangtze River",
      "category": "GK",
      "source": "SSC CHSL 2024",
      "date": "2024-03-05",
      "shift": "Morning"
    },
    {
      "question": "Q95:- The 'National Human Rights Commission' (NHRC) was established in India in which year?",
      "options": [
        "1990",
        "1993",
        "1995",
        "1998"
      ],
      "answer": "1993",
      "category": "GK",
      "source": "SSC MTS 2025",
      "date": "2025-08-01",
      "shift": "Afternoon"
    },
    {
      "question": "Q3:- The smallest country in the world by area is:",
      "options": [
        "Monaco",
        "Vatican City",
        "Nauru",
        "San Marino"
      ],
      "answer": "Vatican City",
      "category": "GK",
      "source": "SSC MTS 2024",
      "date": "2024-05-12",
      "shift": "Morning"
    },
    {
      "question": "Q81:- The 'Tsunami' is caused by:",
      "options": [
        "Strong winds",
        "Undersea earthquakes",
        "Volcanic eruptions",
        "Heavy rainfall"
      ],
      "answer": "Undersea earthquakes",
      "category": "GK",
      "source": "SSC CGL 2025",
      "date": "2025-06-10",
      "shift": "Evening"
    },
    {
      "question": "Q91:- The 'Right to Information Act' (RTI) came into force in India in which year?",
      "options": [
        "2002",
        "2005",
        "2007",
        "2010"
      ],
      "answer": "2005",
      "category": "GK",
      "source": "SSC MTS 2025",
      "date": "2025-07-05",
      "shift": "Morning"
    },
    {
      "question": "Q24:-The first artificial satellite launched by India was:",
      "options": [
        "Rohini",
        "Bhaskara",
        "Aryabhata",
        "Chandrayaan-1"
      ],
      "answer": "Aryabhata",
      "category": "GK",
      "source": "SSC CGL 2020",
      "date": "2020-02-28",
      "shift": "Evening"
    },
    {
      "question": "Q50:- The highest waterfall in the world is:",
      "options": [
        "Niagara Falls",
        "Victoria Falls",
        "Angel Falls",
        "Iguazu Falls"
      ],
      "answer": "Angel Falls",
      "category": "GK",
      "source": "SSC CHSL 2024",
      "date": "2024-09-05",
      "shift": "Morning"
    },
    {
      "question": "Q57:- The 'United Nations Organization' (UNO) was established in which year?",
      "options": [
        "1942",
        "1945",
        "1948",
        "1950"
      ],
      "answer": "1945",
      "category": "GK",
      "source": "SSC CGL 2025",
      "date": "2025-10-01",
      "shift": "Morning"
    },
    {
      "question": "Q84:- The 'UNESCO' headquarters is located in:",
      "options": [
        "Rome",
        "Paris",
        "London",
        "Geneva"
      ],
      "answer": "Paris",
      "category": "GK",
      "source": "SSC GD 2025",
      "date": "2025-05-08",
      "shift": "Afternoon"
    },
    {
      "question": "Q90:- The 'Gobi Desert' is located in:",
      "options": [
        "Africa",
        "South America",
        "Asia",
        "Australia"
      ],
      "answer": "Asia",
      "category": "GK",
      "source": "SSC CHSL 2025",
      "date": "2025-07-22",
      "shift": "Afternoon"
    }
  ]
}