{
  "questions": [
    {
      "question": "Q76:-The number of fundamental duties in the Indian Constitution is:",
      "options": [
        "10",
        "11",
        "12",
        "9"
      ],
      "answer": "11",
      "category": "GK",
      "source": "SSC CGL 2020",
      "date": "2020-03-08",
      "shift": "Morning"
    },
    {
      "question": "Q17:- The largest state in India by area is:",
      "options": [
        "Madhya Pradesh",
        "Maharashtra",
        "Rajasthan",
        "Uttar Pradesh"
      ],
      "answer": "Rajasthan",
      "category": "GK",
      "source": "SSC CGL 2024",
      "date": "2024-11-01",
      "shift": "Morning"
    },
    {
      "question": "Q88:- The 'Green Revolution' in India was led by:",
      "options": [
        "M.S. Swaminathan",
        "Verghese Kurien",
        "Homi J. Bhabha",
        "C.V. Raman"
      ],
      "answer": "M.S. Swaminathan",
      "category": "GK",
      "source": "SSC GD 2025",
      "date": "2025-06-28",
      "shift": "Morning"
    },
    {
      "question": "Q80:- The 'National Emblem of India' is adapted from the Sarnath Lion Capital of Ashoka with the motto:",
      "options": [
        "Jai Hind",
        "Vande Mataram",
        "Satyamev Jayate",
        "Bharat Mata Ki Jai"
      ],
      "answer": "Satyamev Jayate",
      "category": "GK",
      "source": "SSC GD 2025",
      "date": "2025-04-01",
      "shift": "Morning"
    },
    {
      "question": "Q100:- The 'Chadar Trek' is a famous winter trek in which region of India?",
      "options": [
        "Himachal Pradesh",
        "Uttarakhand",
        "Ladakh",
        "Sikkim"
      ],
      "answer": "Ladakh",
      "category": "GK",
      "source": "SSC GD 2025",
      "date": "2025-09-22",
      "shift": "Morning"
    },
    {
      "question": "Q84:-The minimum age for voting in India is:",
      "options": [
        "16 years",
        "18 years",
        "21 years",
        "25 years"
      ],
      "answer": "18 years",
      "category": "GK",
      "source": "SSC CHSL 2020",
      "date": "2020-09-01",
      "shift": "Morning"
    },
    {
      "question": "Q85:-The world's largest flower is:",
      "options": [
        "Rose",
        "Sunflower",
        "Rafflesia Arnoldii",
        "Lotus"
      ],
      "answer": "Rafflesia Arnoldii",
      "category": "GK",
      "source": "SSC MTS 2023",
      "date": "2023-07-15",
      "shift": "Afternoon"
    },
    {
      "question": "Q91:-The instrument used to measure the purity of milk is:",
      "options": [
        "Hydrometer",
        "Lactometer",
        "Barometer",
        "Thermometer"
      ],
      "answer": "Lactometer",
      "category": "GK",
      "source": "SSC CGL 2023",
      "date": "2023-03-01",
      "shift": "Morning"
    },
    {
      "question": "Q77:- The largest plateau in the world is:",
      "options": [
        "Deccan Plateau",
        "Tibetan Plateau",
        "Patagonian Plateau",
        "Colorado Plateau"
      ],
      "answer": "Tibetan Plateau",
      "category": "GK",
      "source": "SSC CGL 2025",
      "date": "2025-05-01",
      "shift": "Morning"
    },
    {
      "question": "Q36:-The highest civilian award in India is:",
      "options": [
        "Padma Vibhushan",
        "Padma Bhushan",
        "Padma Shri",
        "Bharat Ratna"
      ],
      "answer": "Bharat Ratna",
      "category": "GK",
      "source": "SSC CGL 2020",
      "date": "2020-03-02",
      "shift": "Morning"
    }
  ]
}