{
  "questions": [
    {
      "question": "Q23:-The currency of Japan is:",
      "options": [
        "Yuan",
        "Won",
        "Yen",
        "Rupee"
      ],
      "answer": "Yen",
      "category": "GK",
      "source": "SSC GD 2023",
      "date": "2023-02-05",
      "shift": "Afternoon"
    },
    {
      "question": "Q49:-The capital of Australia is:",
      "options": [
        "Sydney",
        "Melbourne",
        "Canberra",
        "Perth"
      ],
      "answer": "Canberra",
      "category": "GK",
      "source": "SSC GD 2023",
      "date": "2023-02-10",
      "shift": "Afternoon"
    },
    {
      "question": "Q57:-The largest producer of coffee in India is:",
      "options": [
        "Kerala",
        "Karnataka",
        "Tamil Nadu",
        "Assam"
      ],
      "answer": "Karnataka",
      "category": "GK",
      "source": "SSC CHSL 2021",
      "date": "2021-08-01",
      "shift": "Morning"
    },
    {
      "question": "Q86:-The 'India Gate' is located in which city?",
      "options": [
        "Mumbai",
        "Kolkata",
        "New Delhi",
        "Chennai"
      ],
      "answer": "New Delhi",
      "category": "GK",
      "source": "SSC CGL 2023",
      "date": "2023-02-28",
      "shift": "Morning"
    },
    {
      "question": "Q44:-The famous 'Ajanta Caves' are located in which state?",
      "options": [
        "Maharashtra",
        "Madhya Pradesh",
        "Karnataka",
        "Rajasthan"
      ],
      "answer": "Maharashtra",
      "category": "GK",
      "source": "SSC CHSL 2020",
      "date": "2020-09-18",
      "shift": "Evening"
    },
    {
      "question": "Q64:- The term 'Offside' is associated with which sport?",
      "options": [
        "Cricket",
        "Football",
        "Hockey",
        "Basketball"
      ],
      "answer": "Football",
      "category": "GK",
      "source": "SSC GD 2025",
      "date": "2025-11-25",
      "shift": "Afternoon"
    },
    {
      "question": "Q2:- Which Indian city is known as the 'Silicon Valley of India'?",
      "options": [
        "Mumbai",
        "Hyderabad",
        "Bengaluru",
        "Chennai"
      ],
      "answer": "Bengaluru",
      "category": "GK",
      "source": "SSC CHSL 2023",
      "date": "2023-06-10",
      "shift": "Evening"
    },
    {
      "question": "Q91:-The instrument used to measure the purity of milk is:",
      "options": [
        "Hydrometer",
        "Lactometer",
        "Barometer",
        "Thermometer"
      ],
      "answer": "Lactometer",
      "category": "GK",
      "source": "SSC CGL 2023",
      "date": "2023-03-01",
      "shift": "Morning"
    },
    {
      "question": "Q3:- The smallest country in the world by area is:",
      "options": [
        "Monaco",
        "Vatican City",
        "Nauru",
        "San Marino"
      ],
      "answer": "Vatican City",
      "category": "GK",
      "source": "SSC MTS 2024",
      "date": "2024-05-12",
      "shift": "Morning"
    },
    {
      "question": "Q69:-The first Indian to receive the Nobel Prize was:",
      "options": [
        "C. V. Raman",
        "Mother Teresa",
        "Rabindranath Tagore",
        "Amartya Sen"
      ],
      "answer": "Rabindranath Tagore",
      "category": "GK",
      "source": "SSC GD 2023",
      "date": "2023-03-05",
      "shift": "Morning"
    }
  ]
}