{
  "questions": [
    {
      "question": "Q47:- The smallest Union Territory in India by population is:",
      "options": [
        "Chandigarh",
        "Lakshadweep",
        "Daman and Diu",
        "Puducherry"
      ],
      "answer": "Lakshadweep",
      "category": "GK",
      "source": "SSC MTS 2025",
      "date": "2025-07-10",
      "shift": "Morning"
    },
    {
      "question": "Q87:- The 'Kochi International Airport' is the first airport in the world to be fully powered by:",
      "options": [
        "Wind energy",
        "Solar energy",
        "Hydroelectric energy",
        "Geothermal energy"
      ],
      "answer": "Solar energy",
      "category": "GK",
      "source": "SSC MTS 2025",
      "date": "2025-06-20",
      "shift": "Evening"
    },
    {
      "question": "Q62:- Who founded the 'Sikhism' religion?",
      "options": [
        "Guru Gobind Singh",
        "Guru Nanak Dev",
        "Guru Arjan Dev",
        "Guru Tegh Bahadur"
      ],
      "answer": "Guru Nanak Dev",
      "category": "GK",
      "source": "SSC CHSL 2024",
      "date": "2024-12-10",
      "shift": "Morning"
    },
    {
      "question": "Q71:-The gas used in balloons and airships is:",
      "options": [
        "Oxygen",
        "Nitrogen",
        "Helium",
        "Argon"
      ],
      "answer": "Helium",
      "category": "GK",
      "source": "SSC CGL 2023",
      "date": "2023-07-01",
      "shift": "Morning"
    },
    {
      "question": "Q82:-The 'National Science Day' in India is celebrated on:",
      "options": [
        "January 15",
        "February 28",
        "March 22",
        "April 7"
      ],
      "answer": "February 28",
      "category": "GK",
      "source": "SSC GD 2022",
      "date": "2022-12-18",
      "shift": "Morning"
    },
    {
      "question": "Q79:-The sport of 'Kabaddi' originated in which country?",
      "options": [
        "China",
        "India",
        "Bangladesh",
        "Nepal"
      ],
      "answer": "India",
      "category": "GK",
      "source": "SSC MTS 2023",
      "date": "2023-06-20",
      "shift": "Morning"
    },
    {
      "question": "Q21:- The largest democracy in the world is:",
      "options": [
        "USA",
        "India",
        "China",
        "Canada"
      ],
      "answer": "India",
      "category": "GK",
      "source": "SSC CGL 2024",
      "date": "2024-12-05",
      "shift": "Evening"
    },
    {
      "question": "Q8:-What is the capital of Arunachal Pradesh?",
      "options": [
        "Itanagar",
        "Dispur",
        "Guwahati",
        "Shillong"
      ],
      "answer": "Itanagar",
      "category": "GK",
      "source": "SSC CHSL 2020",
      "date": "2020-08-11",
      "shift": "Evening"
    },
    {
      "question": "Q76:- The 'Bicameral Legislature' means:",
      "options": [
        "One House of Parliament",
        "Two Houses of Parliament",
        "Three Houses of Parliament",
        "No Houses of Parliament"
      ],
      "answer": "Two Houses of Parliament",
      "category": "GK",
      "source": "SSC GD 2025",
      "date": "2025-03-25",
      "shift": "Evening"
    },
    {
      "question": "Q23:-The currency of Japan is:",
      "options": [
        "Yuan",
        "Won",
        "Yen",
        "Rupee"
      ],
      "answer": "Yen",
      "category": "GK",
      "source": "SSC GD 2023",
      "date": "2023-02-05",
      "shift": "Afternoon"
    }
  ]
}