{
  "questions": [
    {
      "question": "Q23:-The currency of Japan is:",
      "options": [
        "Yuan",
        "Won",
        "Yen",
        "Rupee"
      ],
      "answer": "Yen",
      "category": "GK",
      "source": "SSC GD 2023",
      "date": "2023-02-05",
      "shift": "Afternoon"
    },
    {
      "question": "Q89:-The 'International Yoga Day' is celebrated on:",
      "options": [
        "June 5",
        "June 21",
        "July 11",
        "August 12"
      ],
      "answer": "June 21",
      "category": "GK",
      "source": "SSC GD 2023",
      "date": "2023-01-30",
      "shift": "Afternoon"
    },
    {
      "question": "Q80:- The 'National Emblem of India' is adapted from the Sarnath Lion Capital of Ashoka with the motto:",
      "options": [
        "Jai Hind",
        "Vande Mataram",
        "Satyamev Jayate",
        "Bharat Mata Ki Jai"
      ],
      "answer": "Satyamev Jayate",
      "category": "GK",
      "source": "SSC GD 2025",
      "date": "2025-04-01",
      "shift": "Morning"
    },
    {
      "question": "Q4:- Who wrote the epic 'Ramayana'?",
      "options": [
        "Valmiki",
        "Tulsidas",
        "Vyasa",
        "Kalidasa"
      ],
      "answer": "Valmiki",
      "category": "GK",
      "source": "SSC GD 2024",
      "date": "2024-01-25",
      "shift": "Afternoon"
    },
    {
      "question": "Q31:-The smallest ocean in the world is:",
      "options": [
        "Indian Ocean",
        "Atlantic Ocean",
        "Arctic Ocean",
        "Southern Ocean"
      ],
      "answer": "Arctic Ocean",
      "category": "GK",
      "source": "SSC CGL 2023",
      "date": "2023-01-05",
      "shift": "Morning"
    },
    {
      "question": "Q57:-The largest producer of coffee in India is:",
      "options": [
        "Kerala",
        "Karnataka",
        "Tamil Nadu",
        "Assam"
      ],
      "answer": "Karnataka",
      "category": "GK",
      "source": "SSC CHSL 2021",
      "date": "2021-08-01",
      "shift": "Morning"
    },
    {
      "question": "Q81:- The 'Tsunami' is caused by:",
      "options": [
        "Strong winds",
        "Undersea earthquakes",
        "Volcanic eruptions",
        "Heavy rainfall"
      ],
      "answer": "Undersea earthquakes",
      "category": "GK",
      "source": "SSC CGL 2025",
      "date": "2025-06-10",
      "shift": "Evening"
    },
    {
      "question": "Q92:-The 'National Emblem of India' is adapted from the Sarnath Lion Capital of Ashoka with the motto:",
      "options": [
        "Satyamev Jayate",
        "Vande Mataram",
        "Jai Hind",
        "Incredible India"
      ],
      "answer": "Satyamev Jayate",
      "category": "GK",
      "source": "SSC CHSL 2022",
      "date": "2022-05-25",
      "shift": "Evening"
    },
    {
      "question": "Q28:- Who invented the light bulb?",
      "options": [
        "Alexander Graham Bell",
        "Thomas Edison",
        "Nikola Tesla",
        "Marie Curie"
      ],
      "answer": "Thomas Edison",
      "category": "GK",
      "source": "SSC GD 2025",
      "date": "2025-02-01",
      "shift": "Morning"
    },
    {
      "question": "Q93:-Which continent has no deserts?",
      "options": [
        "Asia",
        "Europe",
        "Africa",
        "North America"
      ],
      "answer": "Europe",
      "category": "GK",
      "source": "SSC CGL 2021",
      "date": "2021-07-01",
      "shift": "Afternoon"
    }
  ]
}